volttron/__no_init_here__
volttron/services/web/__init__.py
volttron/services/web/admin_endpoints.py
volttron/services/web/authenticate_endpoint.py
volttron/services/web/csr_endpoints.py
volttron/services/web/discovery.py
volttron/services/web/platform_web_service.py
volttron/services/web/static/index.html
volttron/services/web/static/js/jquery-3.5.0.min.js
volttron/services/web/static/logo-tagline.png
volttron/services/web/static/specs/vui.specs.yml
volttron/services/web/templates/base.html
volttron/services/web/templates/create_csr.html
volttron/services/web/templates/first.html
volttron/services/web/templates/index.html
volttron/services/web/templates/list_certs.html
volttron/services/web/templates/login.html
volttron/services/web/templates/pending_auth_reqs.html
volttron/services/web/templates/pending_csrs.html
volttron/services/web/topic_tree.py
volttron/services/web/vui_endpoints.py
volttron/services/web/vui_pubsub.py
volttron/services/web/webapp.py
volttron/services/web/websocket.py
volttron_lib_web-0.2.0rc0.dist-info/LICENSE
volttron_lib_web-0.2.0rc0.dist-info/WHEEL
volttron_lib_web-0.2.0rc0.dist-info/METADATA
volttron_lib_web-0.2.0rc0.dist-info/RECORD
