Metadata-Version: 2.1
Name: volttron-lib-web
Version: 0.2.0rc0
Summary: The volttron-lib-web library extends the platform by exposing a web based REST api and allows extension web agents to register with the platform.
Home-page: https://volttron.readthedocs.io
License: 2022
Author: VOLTTRON Team
Author-email: volttron@pnnl.gov
Requires-Python: >=3.8,<4.0
Classifier: License :: Other/Proprietary License
Classifier: Programming Language :: Python :: 3
Classifier: Programming Language :: Python :: 3.8
Classifier: Programming Language :: Python :: 3.9
Classifier: Programming Language :: Python :: 3.10
Classifier: Programming Language :: Python :: 3.11
Requires-Dist: PyJWT (==1.7.1)
Requires-Dist: argon2-cffi (>=21.3.0,<22.0.0)
Requires-Dist: jinja2-cli (>=0.7.0)
Requires-Dist: passlib (>=1.7.4,<2.0.0)
Requires-Dist: requests (>=2.28.1,<3.0.0)
Requires-Dist: treelib (>=1.6.1)
Requires-Dist: volttron (>=10.0.2rc0,<11.0)
Requires-Dist: werkzeug (>=2.1.2)
Requires-Dist: ws4py (>=0.5.1)
Project-URL: Repository, https://github.com/eclipse-volttron/volttron-lib-web
